.coveragerc
.coveralls.yml
.gitignore
.travis.yml
MANIFEST.in
README.rst
manage.py
setup.cfg
setup.py
tox.ini
django_related_admin.egg-info/PKG-INFO
django_related_admin.egg-info/SOURCES.txt
django_related_admin.egg-info/dependency_links.txt
django_related_admin.egg-info/requires.txt
django_related_admin.egg-info/top_level.txt
related_admin/__init__.py
related_admin/compat.py
related_admin/templates/admin/change_list.html
test_app/__init__.py
test_app/settings.py
test_app/tests.py
test_app/urls.py
test_app/wsgi.py
test_app/main/__init__.py
test_app/main/admin.py
test_app/main/models.py
test_app/main/fixtures/data.json
test_app/main/migrations/0001_initial.py
test_app/main/migrations/0002_auto_20160110_0045.py
test_app/main/migrations/0003_auto_20160612_0933.py
test_app/main/migrations/0004_musician_active.py
test_app/main/migrations/0005_auto_20180908_2249.py
test_app/main/migrations/__init__.py